{
  "url" : "https://github.com/stefvanschie/IF/pull/1951",
  "project" : "IF",
  "projectOrganisation" : "stefvanschie",
  "breakingCommit" : "187fdcf9c709e80054da7ec5f610a5379a5f65b1",
  "prAuthor" : "bot",
  "preCommitAuthor" : "human",
  "breakingCommitAuthor" : "bot",
  "updatedDependency" : {
    "dependencyGroupID" : "org.jetbrains",
    "dependencyArtifactID" : "annotations",
    "previousVersion" : "26.0.1",
    "newVersion" : "26.0.2",
    "dependencyScope" : "provided",
    "versionUpdateType" : "patch",
    "dependencySection" : "unknown"
  },
  "licenseInfo" : "The Unlicense"
}