{
  "url" : "https://github.com/eXist-db/exist/pull/5446",
  "project" : "exist",
  "projectOrganisation" : "eXist-db",
  "breakingCommit" : "2f834de4f17eddd4acd84fe1847cd2b841a09913",
  "prAuthor" : "bot",
  "preCommitAuthor" : "human",
  "breakingCommitAuthor" : "bot",
  "updatedDependency" : {
    "dependencyGroupID" : "commons-io",
    "dependencyArtifactID" : "commons-io",
    "previousVersion" : "2.16.1",
    "newVersion" : "2.17.0",
    "dependencyScope" : "compile",
    "versionUpdateType" : "minor",
    "dependencySection" : "dependencyManagement"
  },
  "licenseInfo" : "GNU Lesser General Public License v2.1"
}