{
  "url" : "https://github.com/quarkusio/quarkus-platform/pull/1270",
  "project" : "quarkus-platform",
  "projectOrganisation" : "quarkusio",
  "breakingCommit" : "4d21d1578350135f7d86da38eef0768f1432850f",
  "prAuthor" : "bot",
  "preCommitAuthor" : "human",
  "breakingCommitAuthor" : "bot",
  "updatedDependency" : {
    "dependencyGroupID" : "ca.uhn.hapi.fhir",
    "dependencyArtifactID" : "org.hl7.fhir.dstu2016may",
    "previousVersion" : "6.1.2.2",
    "newVersion" : "6.3.23",
    "dependencyScope" : "compile",
    "versionUpdateType" : "other",
    "dependencySection" : "dependencyManagement"
  },
  "licenseInfo" : "Apache License 2.0"
}