{
  "url" : "https://github.com/drftpd-ng/drftpd/pull/423",
  "project" : "drftpd",
  "projectOrganisation" : "drftpd-ng",
  "breakingCommit" : "618111b81b89c61e1cc8fc5be4d39c54952270a5",
  "prAuthor" : "bot",
  "preCommitAuthor" : "human",
  "breakingCommitAuthor" : "bot",
  "updatedDependency" : {
    "dependencyGroupID" : "com.cedarsoftware",
    "dependencyArtifactID" : "json-io",
    "previousVersion" : "4.14.2",
    "newVersion" : "4.28.0",
    "dependencyScope" : "compile",
    "versionUpdateType" : "minor",
    "dependencySection" : "dependencies"
  },
  "licenseInfo" : "GNU General Public License v2.0"
}