{
  "url" : "https://github.com/liquibase/liquibase/pull/6815",
  "project" : "liquibase",
  "projectOrganisation" : "liquibase",
  "breakingCommit" : "9cf00edc5bced9379cc81fc0973de17de6474df1",
  "prAuthor" : "bot",
  "preCommitAuthor" : "human",
  "breakingCommitAuthor" : "bot",
  "updatedDependency" : {
    "dependencyGroupID" : "org.junit.platform",
    "dependencyArtifactID" : "junit-platform-suite",
    "previousVersion" : "1.11.4",
    "newVersion" : "1.12.1",
    "dependencyScope" : "compile",
    "versionUpdateType" : "minor",
    "dependencySection" : "dependencies"
  },
  "licenseInfo" : "Apache License 2.0"
}