{
  "url" : "https://github.com/camunda/camunda/pull/20974",
  "project" : "camunda",
  "projectOrganisation" : "camunda",
  "breakingCommit" : "9f6251ae92d9304bf887561abc883192aa4c8105",
  "prAuthor" : "bot",
  "preCommitAuthor" : "bot",
  "breakingCommitAuthor" : "bot",
  "updatedDependency" : {
    "dependencyGroupID" : "io.github.classgraph",
    "dependencyArtifactID" : "classgraph",
    "previousVersion" : "4.8.172",
    "newVersion" : "4.8.174",
    "dependencyScope" : "compile",
    "versionUpdateType" : "patch",
    "dependencySection" : "dependencies"
  },
  "licenseInfo" : "unknown"
}