{
  "url" : "https://github.com/jenkinsci/declarative-pipeline-migration-assistant-plugin/pull/293",
  "project" : "declarative-pipeline-migration-assistant-plugin",
  "projectOrganisation" : "jenkinsci",
  "breakingCommit" : "b8bbc52aeedcc8f27c465234f4dc35f9f4fab3af",
  "prAuthor" : "bot",
  "preCommitAuthor" : "human",
  "breakingCommitAuthor" : "bot",
  "updatedDependency" : {
    "dependencyGroupID" : "io.jenkins.tools.bom",
    "dependencyArtifactID" : "bom-${jenkins.baseline}.x",
    "previousVersion" : "3944.v1a_e4f8b_452db_",
    "newVersion" : "4440.v39a_9eb_b_c6b_4d",
    "dependencyScope" : "import",
    "versionUpdateType" : "other",
    "dependencySection" : "unknown"
  },
  "licenseInfo" : "MIT License"
}