{
  "url" : "https://github.com/digital-preservation/droid/pull/1239",
  "project" : "droid",
  "projectOrganisation" : "digital-preservation",
  "breakingCommit" : "cf06d8e918998fa223567aa89b437ae4a7e02db1",
  "prAuthor" : "bot",
  "preCommitAuthor" : "human",
  "breakingCommitAuthor" : "bot",
  "updatedDependency" : {
    "dependencyGroupID" : "software.amazon.awssdk",
    "dependencyArtifactID" : "ssooidc",
    "previousVersion" : "2.31.10",
    "newVersion" : "2.31.11",
    "dependencyScope" : "compile",
    "versionUpdateType" : "patch",
    "dependencySection" : "dependencies"
  },
  "licenseInfo" : "BSD 3-Clause \"New\" or \"Revised\" License"
}